neo4j_parallel_spark_loader/__init__.py
neo4j_parallel_spark_loader/bipartite/__init__.py
neo4j_parallel_spark_loader/bipartite/batching.py
neo4j_parallel_spark_loader/bipartite/grouping.py
neo4j_parallel_spark_loader/bipartite/grouping_and_batching.py
neo4j_parallel_spark_loader/monopartite/__init__.py
neo4j_parallel_spark_loader/monopartite/batching.py
neo4j_parallel_spark_loader/monopartite/grouping.py
neo4j_parallel_spark_loader/monopartite/grouping_and_batching.py
neo4j_parallel_spark_loader/predefined_components/__init__.py
neo4j_parallel_spark_loader/predefined_components/batching.py
neo4j_parallel_spark_loader/predefined_components/grouping.py
neo4j_parallel_spark_loader/predefined_components/grouping_and_batching.py
neo4j_parallel_spark_loader/utils/__init__.py
neo4j_parallel_spark_loader/utils/build_relationship.py
neo4j_parallel_spark_loader/utils/grouping.py
neo4j_parallel_spark_loader/utils/ingest.py
neo4j_parallel_spark_loader/utils/verify_spark.py
neo4j_parallel_spark_loader/visualize/__init__.py
neo4j_parallel_spark_loader/visualize/heatmap.py
neo4j_parallel_spark_loader-0.5.2.dist-info/LICENSE
neo4j_parallel_spark_loader-0.5.2.dist-info/METADATA
neo4j_parallel_spark_loader-0.5.2.dist-info/WHEEL
neo4j_parallel_spark_loader-0.5.2.dist-info/RECORD
