Metadata-Version: 2.3
Name: neo4j-parallel-spark-loader
Version: 0.5.2
Summary: Load relationships in parallel into Neo4j using Spark
Author: Alex Gilmore
Requires-Python: >=3.10,<4.0
Classifier: Programming Language :: Python :: 3
Classifier: Programming Language :: Python :: 3.10
Classifier: Programming Language :: Python :: 3.11
Classifier: Programming Language :: Python :: 3.12
Classifier: Programming Language :: Python :: 3.13
Requires-Dist: numpy (>=1.2.0,<2.0.0)
Requires-Dist: pyspark (>=3.4.0,<4.0.0)
